LICENSE
README.md
setup.cfg
setup.py
orange_utils/__init__.py
orange_utils/cache.py
orange_utils/component.py
orange_utils/file.py
orange_utils/utils.py
orange_utils.egg-info/PKG-INFO
orange_utils.egg-info/SOURCES.txt
orange_utils.egg-info/dependency_links.txt
orange_utils.egg-info/top_level.txt