Metadata-Version: 2.1
Name: orange-utils
Version: 0.1
Summary: orange utils
Home-page: https://github.com/aminnewgit/OrangeKit
Download-URL: https://github.com/aminnewgit/OrangeKit/dist/orange_utils-0.1.tar.gz
Author: junjun
Author-email: 289584104@qq.com
License: MIT
Keywords: orange,data class,
Classifier: Development Status :: 3 - Alpha
Classifier: Intended Audience :: Developers
Classifier: Topic :: Software Development :: Build Tools
Classifier: License :: OSI Approved :: MIT License
Classifier: Programming Language :: Python :: 3.6
Classifier: Programming Language :: Python :: 3.7
Classifier: Programming Language :: Python :: 3.8
Classifier: Programming Language :: Python :: 3.9
Classifier: Programming Language :: Python :: 3.10
Classifier: Programming Language :: Python :: 3.11
License-File: LICENSE
